{
  "$schema": "https://developer.microsoft.com/json-schemas/fabric/item/report/definition/visualContainer/2.11.0/schema.json",
  "name": "726d4be0105e102ea430",
  "position": {
    "x": 19.2,
    "y": 10.8,
    "z": 2000,
    "width": 960,
    "height": 54,
    "tabOrder": 2000
  },
  "visual": {
    "visualType": "textbox",
    "drillFilterOtherVisuals": true,
    "objects": {
      "general": [
        {
          "properties": {
            "paragraphs": [
              {
                "horizontalTextAlignment": "left",
                "textRuns": [
                  {
                    "value": "Super Sample Superstore Dashboard",
                    "textStyle": {
                      "fontFamily": "Segoe UI Semibold",
                      "fontSize": "20pt",
                      "color": "#FFFFFF"
                    }
                  }
                ]
              }
            ]
          }
        }
      ]
    },
    "visualContainerObjects": {
      "border": [
        {
          "properties": {
            "show": {
              "expr": {
                "Literal": {
                  "Value": "false"
                }
              }
            }
          }
        }
      ]
    }
  }
}