{
  "$schema": "https://developer.microsoft.com/json-schemas/fabric/item/report/definition/visualContainer/2.11.0/schema.json",
  "name": "9a5a85c5557803c400b7",
  "position": {
    "x": 1148.5,
    "y": 532,
    "z": 5000,
    "height": 56,
    "width": 204.5,
    "tabOrder": 0
  },
  "visual": {
    "visualType": "cardVisual",
    "query": {
      "queryState": {
        "Data": {
          "projections": [
            {
              "field": {
                "Aggregation": {
                  "Expression": {
                    "Column": {
                      "Expression": {
                        "SourceRef": {
                          "Entity": "Flight Activity"
                        }
                      },
                      "Property": "Fuel Cost Usd"
                    }
                  },
                  "Function": 0
                }
              },
              "queryRef": "Sum(Flight Activity.Fuel Cost Usd)",
              "nativeQueryRef": "Fuel Cost Usd",
              "displayName": "Total Fuel Cost ($)"
            }
          ]
        }
      }
    },
    "objects": {
      "value": [
        {
          "properties": {
            "fontSize": {
              "expr": {
                "Literal": {
                  "Value": "17D"
                }
              }
            },
            "bold": {
              "expr": {
                "Literal": {
                  "Value": "true"
                }
              }
            },
            "fontColor": {
              "solid": {
                "color": {
                  "expr": {
                    "Literal": {
                      "Value": "'#1A1A2E'"
                    }
                  }
                }
              }
            },
            "labelDisplayUnits": {
              "expr": {
                "Literal": {
                  "Value": "'1000000000'"
                }
              }
            },
            "labelPrecision": {
              "expr": {
                "Literal": {
                  "Value": "2D"
                }
              }
            }
          },
          "selector": {
            "id": "default"
          }
        }
      ],
      "label": [
        {
          "properties": {
            "show": {
              "expr": {
                "Literal": {
                  "Value": "true"
                }
              }
            },
            "position": {
              "expr": {
                "Literal": {
                  "Value": "'aboveValue'"
                }
              }
            },
            "fontSize": {
              "expr": {
                "Literal": {
                  "Value": "8D"
                }
              }
            },
            "fontColor": {
              "solid": {
                "color": {
                  "expr": {
                    "Literal": {
                      "Value": "'#6A6A7E'"
                    }
                  }
                }
              }
            }
          },
          "selector": {
            "id": "default"
          }
        }
      ],
      "divider": [
        {
          "properties": {
            "show": {
              "expr": {
                "Literal": {
                  "Value": "false"
                }
              }
            }
          },
          "selector": {
            "id": "default"
          }
        }
      ]
    },
    "visualContainerObjects": {
      "title": [
        {
          "properties": {
            "show": {
              "expr": {
                "Literal": {
                  "Value": "false"
                }
              }
            }
          }
        }
      ]
    },
    "drillFilterOtherVisuals": true
  },
  "filterConfig": {
    "filters": [
      {
        "name": "Filter3368c6cf36f712a558e1",
        "field": {
          "Column": {
            "Expression": {
              "SourceRef": {
                "Entity": "Flight Activity"
              }
            },
            "Property": "Aircraft Type"
          }
        },
        "type": "Categorical",
        "filter": {
          "Version": 2,
          "From": [
            {
              "Name": "s",
              "Entity": "Flight Activity",
              "Type": 0
            }
          ],
          "Where": [
            {
              "Condition": {
                "In": {
                  "Expressions": [
                    {
                      "Column": {
                        "Expression": {
                          "SourceRef": {
                            "Source": "s"
                          }
                        },
                        "Property": "Aircraft Type"
                      }
                    }
                  ],
                  "Values": [
                    [
                      {
                        "Literal": {
                          "Value": "'A330'"
                        }
                      }
                    ]
                  ]
                }
              }
            }
          ]
        },
        "howCreated": "User"
      }
    ]
  }
}