{
  "$schema": "https://developer.microsoft.com/json-schemas/fabric/item/report/definition/visualContainer/2.11.0/schema.json",
  "name": "82a343098cf2c329cebb",
  "position": { "x": 672, "y": 658.8, "z": 24000, "width": 576, "height": 194.4, "tabOrder": 24000 },
  "visual": {
    "visualType": "lineChart",
    "drillFilterOtherVisuals": true,
    "query": {
      "queryState": {
        "Category": {
          "projections": [
            { "field": { "Column": { "Expression": { "SourceRef": { "Entity": "Date Granularity" } }, "Property": "Date Granularity" } },
              "queryRef": "Date Granularity.Date Granularity", "nativeQueryRef": "Date Granularity", "active": true }
          ]
        },
        "Y": {
          "projections": [
            { "field": { "Measure": { "Expression": { "SourceRef": { "Entity": "Sample Superstore" } }, "Property": "CP Profit Ratio (Trend)" } },
              "queryRef": "Sample Superstore.CP Profit Ratio (Trend)", "nativeQueryRef": "CP Profit Ratio (Trend)" },
            { "field": { "Measure": { "Expression": { "SourceRef": { "Entity": "Sample Superstore" } }, "Property": "PP Profit Ratio (Trend)" } },
              "queryRef": "Sample Superstore.PP Profit Ratio (Trend)", "nativeQueryRef": "PP Profit Ratio (Trend)" }
          ]
        }
      }
    },
    "objects": {
      "categoryAxis": [ { "properties": {
        "showAxisTitle": { "expr": { "Literal": { "Value": "false" } } },
        "fontSize": { "expr": { "Literal": { "Value": "8D" } } }
      } } ],
      "valueAxis": [ { "properties": { "show": { "expr": { "Literal": { "Value": "false" } } } } } ],
      "legend": [ { "properties": { "show": { "expr": { "Literal": { "Value": "false" } } } } } ],
      "dataPoint": [
        { "properties": { "fill": { "solid": { "color": { "expr": { "Literal": { "Value": "'#34657F'" } } } } } },
          "selector": { "metadata": "Sample Superstore.CP Profit Ratio (Trend)" } },
        { "properties": { "fill": { "solid": { "color": { "expr": { "Literal": { "Value": "'#BFBFBF'" } } } } } },
          "selector": { "metadata": "Sample Superstore.PP Profit Ratio (Trend)" } }
      ]
    },
    "visualContainerObjects": {
      "title": [ { "properties": {
        "show": { "expr": { "Literal": { "Value": "false" } } },
        "text": { "expr": { "Literal": { "Value": "'PROFIT RATIO'" } } }
      } } ],
      "background": [ { "properties": { "show": { "expr": { "Literal": { "Value": "false" } } } } } ],
      "border": [ { "properties": { "show": { "expr": { "Literal": { "Value": "false" } } } } } ],
      "padding": [ { "properties": {
        "top": { "expr": { "Literal": { "Value": "0D" } } }, "bottom": { "expr": { "Literal": { "Value": "0D" } } },
        "left": { "expr": { "Literal": { "Value": "0D" } } }, "right": { "expr": { "Literal": { "Value": "0D" } } }
      } } ]
    }
  },
  "filterConfig": {
    "filters": [
      {
        "name": "flt_window_82a343098cf2c329cebb",
        "field": { "Measure": { "Expression": { "SourceRef": { "Entity": "Sample Superstore" } }, "Property": "CP Sales" } },
        "type": "Advanced",
        "filter": {
          "Version": 2,
          "From": [ { "Name": "s", "Entity": "Sample Superstore", "Type": 0 } ],
          "Where": [
            { "Condition": { "Comparison": {
              "ComparisonKind": 1,
              "Left": { "Measure": { "Expression": { "SourceRef": { "Source": "s" } }, "Property": "CP Sales" } },
              "Right": { "Literal": { "Value": "0D" } }
            } } }
          ]
        },
        "howCreated": "User"
      }
    ]
  }
}

