{
  "$schema": "https://developer.microsoft.com/json-schemas/fabric/item/report/definition/visualContainer/2.11.0/schema.json",
  "name": "296393b90647c7f29aed",
  "position": {
    "x": 72,
    "y": 2388,
    "z": 2000,
    "height": 34,
    "width": 1176,
    "tabOrder": 2000
  },
  "visual": {
    "visualType": "textbox",
    "objects": {
      "general": [
        {
          "properties": {
            "paragraphs": [
              {
                "horizontalTextAlignment": "left",
                "textRuns": [
                  {
                    "value": "5 \u00b7 The snake",
                    "textStyle": {
                      "fontFamily": "Segoe UI Semibold",
                      "fontSize": "15pt",
                      "color": "#152835",
                      "fontWeight": "bold"
                    }
                  }
                ]
              }
            ]
          }
        }
      ]
    },
    "visualContainerObjects": {
      "border": [
        {
          "properties": {
            "show": {
              "expr": {
                "Literal": {
                  "Value": "false"
                }
              }
            }
          }
        }
      ],
      "padding": [
        {
          "properties": {
            "top": {
              "expr": {
                "Literal": {
                  "Value": "0D"
                }
              }
            },
            "bottom": {
              "expr": {
                "Literal": {
                  "Value": "0D"
                }
              }
            },
            "left": {
              "expr": {
                "Literal": {
                  "Value": "0D"
                }
              }
            },
            "right": {
              "expr": {
                "Literal": {
                  "Value": "0D"
                }
              }
            }
          }
        }
      ]
    },
    "drillFilterOtherVisuals": true
  }
}